[
{"src": ["https://dxsdcl7y7vn9x.cloudfront.net/414820/4D2458FB-3FBA-49DC-85B7-898FF007727E_1.jpg", "https://dxsdcl7y7vn9x.cloudfront.net/414820/4D2458FB-3FBA-49DC-85B7-898FF007727E_2.jpg", "https://dxsdcl7y7vn9x.cloudfront.net/414820/4D2458FB-3FBA-49DC-85B7-898FF007727E_3.jpg", "https://dxsdcl7y7vn9x.cloudfront.net/414820/4D2458FB-3FBA-49DC-85B7-898FF007727E_4.jpg", "https://dxsdcl7y7vn9x.cloudfront.net/414820/4D2458FB-3FBA-49DC-85B7-898FF007727E_5.jpg", "https://dxsdcl7y7vn9x.cloudfront.net/414820/4D2458FB-3FBA-49DC-85B7-898FF007727E_6.jpg", "https://dxsdcl7y7vn9x.cloudfront.net/414820/4D2458FB-3FBA-49DC-85B7-898FF007727E_7.jpg", "https://dxsdcl7y7vn9x.cloudfront.net/414820/4D2458FB-3FBA-49DC-85B7-898FF007727E_8.jpg", "https://dxsdcl7y7vn9x.cloudfront.net/414820/4D2458FB-3FBA-49DC-85B7-898FF007727E_9.jpg", "https://dxsdcl7y7vn9x.cloudfront.net/414820/4D2458FB-3FBA-49DC-85B7-898FF007727E_10.jpg", "https://dxsdcl7y7vn9x.cloudfront.net/414820/4D2458FB-3FBA-49DC-85B7-898FF007727E_11.jpg", "https://dxsdcl7y7vn9x.cloudfront.net/414820/4D2458FB-3FBA-49DC-85B7-898FF007727E_12.jpg"], "mileage": "84000", "description": ["Inline 6 3.3l, 3 speed automatic, 84k miles, CD player", "Call me 865-681-2366", "Morelock Motors", "2525 East Lamar Alexander Parkway", "Maryville, TN 37804"], "title": "1981 Ford Mustang ", "total_results": "5", "price": "1650", "kilometers": 135156.0, "total_pages": 2, "href": "https://www.carsforsale.com/vehicle/details/26470481", "brand": "Ford", "reference_id": "26470481", "year": "1981", "model": "Mustang", "specs": {"Engine": "3.3L I6", "Mileage": "84,000 miles", "Exterior Color": "Blue", "Transmission": "Automatic 3-Speed", "Interior Color": "Blue", "Drive Train": "RWD", "Fuel": "Gasoline"}},
{"src": ["https://cdn04.carsforsale.com/3/650817/2610783/542840001.jpg", "https://cdn04.carsforsale.com/3/650817/2610783/542840002.jpg", "https://cdn04.carsforsale.com/3/650817/2610783/542840003.jpg", "https://cdn04.carsforsale.com/3/650817/2610783/542840004.jpg", "https://cdn04.carsforsale.com/3/650817/2610783/542840005.jpg", "https://cdn04.carsforsale.com/3/650817/2610783/542840006.jpg", "https://cdn04.carsforsale.com/3/650817/2610783/542840007.jpg", "https://cdn04.carsforsale.com/3/650817/2610783/542840008.jpg", "https://cdn04.carsforsale.com/3/650817/2610783/542840009.jpg", "https://cdn04.carsforsale.com/3/650817/2610783/542840010.jpg", "https://cdn04.carsforsale.com/3/650817/2610783/542840110.jpg", "https://cdn04.carsforsale.com/3/650817/2610783/542840111.jpg", "https://cdn04.carsforsale.com/3/650817/2610783/542840112.jpg", "https://cdn04.carsforsale.com/3/650817/2610783/542840113.jpg", "https://cdn04.carsforsale.com/3/650817/2610783/542840114.jpg", "https://cdn04.carsforsale.com/3/650817/2610783/542840115.jpg", "https://cdn04.carsforsale.com/3/650817/2610783/542840116.jpg", "https://cdn04.carsforsale.com/3/650817/2610783/542840117.jpg", "https://cdn04.carsforsale.com/3/650817/2610783/542840118.jpg", "https://cdn04.carsforsale.com/3/650817/2610783/542840119.jpg", "https://cdn04.carsforsale.com/3/650817/2610783/542840434.jpg", "https://cdn04.carsforsale.com/3/650817/2610783/542840435.jpg", "https://cdn04.carsforsale.com/3/650817/2610783/542840436.jpg", "https://cdn04.carsforsale.com/3/650817/2610783/542840437.jpg", "https://cdn04.carsforsale.com/3/650817/2610783/542840438.jpg", "https://cdn04.carsforsale.com/3/650817/2610783/542840439.jpg", "https://cdn04.carsforsale.com/3/650817/2610783/542840440.jpg", "https://cdn04.carsforsale.com/3/650817/2610783/542840441.jpg", "https://cdn04.carsforsale.com/3/650817/2610783/542840442.jpg", "https://cdn04.carsforsale.com/3/650817/2610783/542840443.jpg", "https://cdn04.carsforsale.com/3/650817/2610783/542840599.jpg", "https://cdn04.carsforsale.com/3/650817/2610783/542840600.jpg", "https://cdn04.carsforsale.com/3/650817/2610783/542840601.jpg", "https://cdn04.carsforsale.com/3/650817/2610783/542840602.jpg", "https://cdn04.carsforsale.com/3/650817/2610783/542840603.jpg", "https://cdn04.carsforsale.com/3/650817/2610783/542840604.jpg", "https://cdn04.carsforsale.com/3/650817/2610783/542840606.jpg", "https://cdn04.carsforsale.com/3/650817/2610783/542840607.jpg", "https://cdn04.carsforsale.com/3/650817/2610783/542840608.jpg", "https://cdn04.carsforsale.com/3/650817/2610783/542840619.jpg", "https://cdn04.carsforsale.com/3/650817/2610783/542840620.jpg", "https://cdn04.carsforsale.com/3/650817/2610783/542840621.jpg", "https://cdn04.carsforsale.com/3/650817/2610783/542840622.jpg", "https://cdn04.carsforsale.com/3/650817/2610783/542840623.jpg", "https://cdn04.carsforsale.com/3/650817/2610783/542840624.jpg", "https://cdn04.carsforsale.com/3/650817/2610783/542840625.jpg", "https://cdn04.carsforsale.com/3/650817/2610783/542840626.jpg", "https://cdn04.carsforsale.com/3/650817/2610783/542840627.jpg", "https://cdn04.carsforsale.com/3/650817/2610783/542840628.jpg", "https://cdn04.carsforsale.com/3/650817/2610783/542840632.jpg", "https://cdn04.carsforsale.com/3/650817/2610783/542840633.jpg", "https://cdn04.carsforsale.com/3/650817/2610783/542840634.jpg", "https://cdn04.carsforsale.com/3/650817/2610783/542840635.jpg", "https://cdn04.carsforsale.com/3/650817/2610783/542840636.jpg", "https://cdn04.carsforsale.com/3/650817/2610783/542840637.jpg", "https://cdn04.carsforsale.com/3/650817/2610783/542840638.jpg", "https://cdn04.carsforsale.com/3/650817/2610783/542840639.jpg", "https://cdn04.carsforsale.com/3/650817/2610783/542840640.jpg", "https://cdn04.carsforsale.com/3/650817/2610783/542840641.jpg", "https://cdn04.carsforsale.com/3/650817/2610783/542840642.jpg", "https://cdn04.carsforsale.com/3/650817/2610783/542840643.jpg", "https://cdn04.carsforsale.com/3/650817/2610783/542840644.jpg", "https://cdn04.carsforsale.com/3/650817/2610783/542840645.jpg", "https://cdn04.carsforsale.com/3/650817/2610783/542840646.jpg", "https://cdn04.carsforsale.com/3/650817/2610783/542840647.jpg", "https://cdn04.carsforsale.com/3/650817/2610783/542840648.jpg", "https://cdn04.carsforsale.com/3/650817/2610783/542840649.jpg", "https://cdn04.carsforsale.com/3/650817/2610783/542840650.jpg", "https://cdn04.carsforsale.com/3/650817/2610783/542840651.jpg", "https://cdn04.carsforsale.com/3/650817/2610783/542840652.jpg", "https://cdn04.carsforsale.com/3/650817/2610783/542840653.jpg", "https://cdn04.carsforsale.com/3/650817/2610783/542840654.jpg", "https://cdn04.carsforsale.com/3/650817/2610783/542840655.jpg", "https://cdn04.carsforsale.com/3/650817/2610783/542840656.jpg", "https://cdn04.carsforsale.com/3/650817/2610783/542840657.jpg", "https://cdn04.carsforsale.com/3/650817/2610783/542840658.jpg", "https://cdn04.carsforsale.com/3/650817/2610783/850654605.jpg"], "mileage": "23144", "description": ["Just traded-in! We sold this gem right at 3 years ago to a nice fellow and car had just 6300 org miles at that time and car was all org it even had the original white wall tires! Former owner retired Captin Seiple is a car guy and wanted to make this little fella his own so he did a few tasteful addtions so check out this ultra hard to find 2 owner 23k org mile rock solid beauty that he loved and drove it almost 17k miles during his ownership! This car was also featured in June 2013 issue of COLLECTIBLE AUTOMOBILE CAR MAGAZINE they came to feature car when we owned it back in 2013 and you can see what car was when we had it! This is a truly neat Mustang Hatchback! This is one super nice beauty! This car runs smooth quite and drives tight and nice and has been a turn key depandable classic see photo of dead on perfect guages after 30 min drive today with cruise on and cold a/c going! Original owners manual, both sets of keys, original date coded plug wires, original window sticker, Ford shop manuals and brochure on this numbers matching machine! Paint looks all original and chips have been touched over years to keep a clean look and it presents great and still shows super nice, pristine interior, dash, seats and plastics are top notch, nice glass sunroof, clean and very tidy undercarrage, trunk and engine bay! Smooth quite #'s matching 2.3L 4cyl, nice shifting 4-speed, cold ac, it has the desireable reclining bucket seats with console this one has several nice options and yes these were not standard it has cruise, rear defogger, dual sport mirrors, delay wipers, power steering, power disc brakes, factory tinted glass and upgrage tinted glass, upgrade old school look am/fm radio with aux imput and usb-i-phone plug-in, factory turbine wheelcovers included, vent shades, cup holder, nice moom hubcaps with painted factory colormatch wheels with new set of tires 10k ago, class II reciever hitch that he used to tow his canoe plus much more! This is a true docmented ultra low mile beauty remember many can restore one but finding an original 23k org mile one is few and far between! Vehicle is parked in our showroom so please call ahead to set up a time to ck it out!"], "title": "1981 Ford Mustang ", "total_results": "5", "price": "7990", "kilometers": 37238.695999999996, "total_pages": 2, "href": "https://www.carsforsale.com/vehicle/details/17645209", "brand": "Ford", "reference_id": "17645209", "year": "1981", "model": "Mustang", "specs": {"Engine": "2.3L I4", "Mileage": "23,144 miles", "Exterior Color": "Maroon Or Burgundy", "Transmission": "Manual 4-Speed", "Interior Color": "", "Drive Train": "RWD", "Fuel": "Gasoline"}},
{"src": ["https://dxsdcl7y7vn9x.cloudfront.net/351989/9E9F3E92-16F9-43E0-821B-BD8EBE0AA472_1.jpg", "https://dxsdcl7y7vn9x.cloudfront.net/351989/9E9F3E92-16F9-43E0-821B-BD8EBE0AA472_2.jpg", "https://dxsdcl7y7vn9x.cloudfront.net/351989/9E9F3E92-16F9-43E0-821B-BD8EBE0AA472_3.jpg", "https://dxsdcl7y7vn9x.cloudfront.net/351989/9E9F3E92-16F9-43E0-821B-BD8EBE0AA472_4.jpg", "https://dxsdcl7y7vn9x.cloudfront.net/351989/9E9F3E92-16F9-43E0-821B-BD8EBE0AA472_5.jpg", "https://dxsdcl7y7vn9x.cloudfront.net/351989/9E9F3E92-16F9-43E0-821B-BD8EBE0AA472_6.jpg", "https://dxsdcl7y7vn9x.cloudfront.net/351989/9E9F3E92-16F9-43E0-821B-BD8EBE0AA472_7.jpg", "https://dxsdcl7y7vn9x.cloudfront.net/351989/9E9F3E92-16F9-43E0-821B-BD8EBE0AA472_8.jpg", "https://dxsdcl7y7vn9x.cloudfront.net/351989/9E9F3E92-16F9-43E0-821B-BD8EBE0AA472_9.jpg", "https://dxsdcl7y7vn9x.cloudfront.net/351989/9E9F3E92-16F9-43E0-821B-BD8EBE0AA472_10.jpg", "https://dxsdcl7y7vn9x.cloudfront.net/351989/9E9F3E92-16F9-43E0-821B-BD8EBE0AA472_11.jpg", "https://dxsdcl7y7vn9x.cloudfront.net/351989/9E9F3E92-16F9-43E0-821B-BD8EBE0AA472_12.jpg"], "mileage": "", "description": ["1980 Ford Mustang Cobraturn key drag car10.51@128mph on motor 9.90@134 on nitrousIt has fiberglass doors hatch and hoodLexan windows in doors and hatchFull 10 point roll cage car is framed not subframe connectedMoser axlesYukon gears and spool(4:30's) 8.8 rear endUpr tubular front k-member and lower control armsUpr fully adjustable upper and lower rear control armsLakewood drag(90/10) struts and shocksCaster camber platesUpr coil over strut conversion5 gallon fuel cellMoroso battery boxOptima yellow top batteryMotor is a 347 stroker with afr 185 headsSolid roller cam(custom grid from comp cams)Performance automatic c4(no trans brake) Full 5 lug conversion front spindles and disk break 8.8 rear end and a bunch of other spare parts for this carVehicle is located in Meridian ID.Qualified buyers may be eligible for Financing Shipping and Extended Warranties."], "title": "1980 Ford Mustang ", "total_results": "5", "price": "10500", "kilometers": "", "total_pages": 2, "href": "https://www.carsforsale.com/vehicle/details/8206758", "brand": "Ford", "reference_id": "8206758", "year": "1980", "model": "Mustang", "specs": {"Engine": "", "Mileage": "", "Exterior Color": "Custom", "Transmission": "Automatic", "Interior Color": "Custom", "Drive Train": "", "Fuel": ""}},
{"src": ["https://dxsdcl7y7vn9x.cloudfront.net/683333/775007B3-499F-4A71-8189-962D31D4BECF_1.jpg", "https://dxsdcl7y7vn9x.cloudfront.net/683333/775007B3-499F-4A71-8189-962D31D4BECF_2.jpg", "https://dxsdcl7y7vn9x.cloudfront.net/683333/775007B3-499F-4A71-8189-962D31D4BECF_3.jpg", "https://dxsdcl7y7vn9x.cloudfront.net/683333/775007B3-499F-4A71-8189-962D31D4BECF_4.jpg", "https://dxsdcl7y7vn9x.cloudfront.net/683333/775007B3-499F-4A71-8189-962D31D4BECF_5.jpg", "https://dxsdcl7y7vn9x.cloudfront.net/683333/775007B3-499F-4A71-8189-962D31D4BECF_6.jpg", "https://dxsdcl7y7vn9x.cloudfront.net/683333/775007B3-499F-4A71-8189-962D31D4BECF_7.jpg", "https://dxsdcl7y7vn9x.cloudfront.net/683333/775007B3-499F-4A71-8189-962D31D4BECF_8.jpg", "https://dxsdcl7y7vn9x.cloudfront.net/683333/775007B3-499F-4A71-8189-962D31D4BECF_9.jpg", "https://dxsdcl7y7vn9x.cloudfront.net/683333/775007B3-499F-4A71-8189-962D31D4BECF_10.jpg", "https://dxsdcl7y7vn9x.cloudfront.net/683333/775007B3-499F-4A71-8189-962D31D4BECF_11.jpg", "https://dxsdcl7y7vn9x.cloudfront.net/683333/775007B3-499F-4A71-8189-962D31D4BECF_12.jpg"], "mileage": "31785", "description": [" Executive Image Auto Group, Family Owned and Operated For Over 30 Years Centrally Located Where The 91/60/215 Freeways Meet. 1981 TAN ZIMMER GOLDEN SPIRIT RWD V8, 4.2L With 31785 Miles. View our entire inventory online at www.ExecutiveImage.net or call toll-free 951-786-0123 to schedule a test drive."], "title": "1981 Ford Mustang ", "total_results": "5", "price": "25995", "kilometers": 51142.065, "total_pages": 2, "href": "https://www.carsforsale.com/vehicle/details/15970854", "brand": "Ford", "reference_id": "15970854", "year": "1981", "model": "Mustang", "specs": {"Engine": "4.2L V8", "Mileage": "31,785 miles", "Exterior Color": "Tan", "Transmission": "Automatic 3-Speed", "Interior Color": "Brown", "Drive Train": "RWD", "Fuel": "Gasoline"}},
{"src": ["https://dxsdcl7y7vn9x.cloudfront.net/351989/E77A9857-901A-41BA-8E70-17BB55E3D190_1.jpg", "https://dxsdcl7y7vn9x.cloudfront.net/351989/E77A9857-901A-41BA-8E70-17BB55E3D190_2.jpg", "https://dxsdcl7y7vn9x.cloudfront.net/351989/E77A9857-901A-41BA-8E70-17BB55E3D190_3.jpg", "https://dxsdcl7y7vn9x.cloudfront.net/351989/E77A9857-901A-41BA-8E70-17BB55E3D190_4.jpg", "https://dxsdcl7y7vn9x.cloudfront.net/351989/E77A9857-901A-41BA-8E70-17BB55E3D190_5.jpg", "https://dxsdcl7y7vn9x.cloudfront.net/351989/E77A9857-901A-41BA-8E70-17BB55E3D190_6.jpg", "https://dxsdcl7y7vn9x.cloudfront.net/351989/E77A9857-901A-41BA-8E70-17BB55E3D190_7.jpg", "https://dxsdcl7y7vn9x.cloudfront.net/351989/E77A9857-901A-41BA-8E70-17BB55E3D190_8.jpg", "https://dxsdcl7y7vn9x.cloudfront.net/351989/E77A9857-901A-41BA-8E70-17BB55E3D190_9.jpg"], "mileage": "68000", "description": ["1981 Ford Mustang GHIA  ConvertibleThis is a great 1981 mustang GHIA that looks great and still runs like a champ.Equipped with a 5.0 liter V6 cylinder engineAutomatic transmissionRear wheel driveIt has 68000 original miles on itThis mustang was stored during the winter seasons in a cover garageComes with a customized manual convertible top This mustang also come fully equipped with power steering Power windows and door locks tilt steering wheel Cruise control power brake AM FM radio with a 6 disc CD changerThis classic does need a little TLCLocated in Saginaw Township MIFinancing Nationwide Shipping And Warranties Available To Qualified Buyers"], "title": "1981 Ford Mustang ", "total_results": "5", "price": "18500", "kilometers": 109412.0, "total_pages": 2, "href": "https://www.carsforsale.com/vehicle/details/9032532", "brand": "Ford", "reference_id": "9032532", "year": "1981", "model": "Mustang", "specs": {"Engine": "", "Mileage": "68,000 miles", "Exterior Color": "Brown", "Transmission": "Automatic 3-Speed", "Interior Color": "Tan", "Drive Train": "RWD", "Fuel": "Gasoline"}}
]