[
{"src": ["https://assets.hemmings.com/uimage/60207725-770-0@2X.jpg?rev=1", "https://assets.hemmings.com/uimage/60207726-770-0@2X.jpg?rev=1", "https://assets.hemmings.com/uimage/60207727-770-0@2X.jpg?rev=1", "https://assets.hemmings.com/uimage/60207728-770-0@2X.jpg?rev=1", "https://assets.hemmings.com/uimage/60207729-770-0@2X.jpg?rev=1", "https://assets.hemmings.com/uimage/60207730-770-0@2X.jpg?rev=1", "https://assets.hemmings.com/uimage/60207731-770-0@2X.jpg?rev=1", "https://assets.hemmings.com/uimage/60207732-770-0@2X.jpg?rev=1", "https://assets.hemmings.com/uimage/60207733-770-0@2X.jpg?rev=1", "https://assets.hemmings.com/uimage/60207735-770-0@2X.jpg?rev=1", "https://assets.hemmings.com/uimage/60207736-770-0@2X.jpg?rev=1", "https://assets.hemmings.com/uimage/60207737-770-0@2X.jpg?rev=1", "https://assets.hemmings.com/uimage/60207738-770-0@2X.jpg?rev=1", "https://assets.hemmings.com/uimage/60207739-770-0@2X.jpg?rev=1", "https://assets.hemmings.com/uimage/60207740-770-0@2X.jpg?rev=1", "https://assets.hemmings.com/uimage/60207742-770-0@2X.jpg?rev=1", "https://assets.hemmings.com/uimage/60207743-770-0@2X.jpg?rev=1", "https://assets.hemmings.com/uimage/60207744-770-0@2X.jpg?rev=1", "https://assets.hemmings.com/uimage/60207745-770-0@2X.jpg?rev=1", "https://assets.hemmings.com/uimage/60207746-770-0@2X.jpg?rev=1", "https://assets.hemmings.com/uimage/60207747-770-0@2X.jpg?rev=1", "https://assets.hemmings.com/uimage/60207748-770-0@2X.jpg?rev=1", "https://assets.hemmings.com/uimage/60207749-770-0@2X.jpg?rev=1", "https://assets.hemmings.com/uimage/60207750-770-0@2X.jpg?rev=1", "https://assets.hemmings.com/uimage/60207751-770-0@2X.jpg?rev=1", "https://assets.hemmings.com/uimage/60207752-770-0@2X.jpg?rev=1", "https://assets.hemmings.com/uimage/60207753-770-0@2X.jpg?rev=1", "https://assets.hemmings.com/uimage/60207754-770-0@2X.jpg?rev=1", "https://assets.hemmings.com/uimage/60207755-770-0@2X.jpg?rev=1", "https://assets.hemmings.com/uimage/60207756-770-0@2X.jpg?rev=1", "https://assets.hemmings.com/uimage/60207757-770-0@2X.jpg?rev=1", "https://assets.hemmings.com/uimage/60207758-770-0@2X.jpg?rev=1", "https://assets.hemmings.com/uimage/60207759-770-0@2X.jpg?rev=1", "https://assets.hemmings.com/uimage/60207760-770-0@2X.jpg?rev=1", "https://assets.hemmings.com/uimage/60207761-770-0@2X.jpg?rev=1", "https://assets.hemmings.com/uimage/60207762-770-0@2X.jpg?rev=1", "https://assets.hemmings.com/uimage/60207763-770-0@2X.jpg?rev=1", "https://assets.hemmings.com/uimage/60207764-770-0@2X.jpg?rev=1", "https://assets.hemmings.com/uimage/60207765-770-0@2X.jpg?rev=1", "https://assets.hemmings.com/uimage/60207766-770-0@2X.jpg?rev=1", "https://assets.hemmings.com/uimage/60207767-770-0@2X.jpg?rev=1", "https://assets.hemmings.com/uimage/60207768-770-0@2X.jpg?rev=1", "https://assets.hemmings.com/uimage/60207769-770-0@2X.jpg?rev=1", "https://assets.hemmings.com/uimage/60207770-770-0@2X.jpg?rev=1", "https://assets.hemmings.com/uimage/60207771-770-0@2X.jpg?rev=1", "https://assets.hemmings.com/uimage/60207772-770-0@2X.jpg?rev=1", "https://assets.hemmings.com/uimage/60207773-770-0@2X.jpg?rev=1", "https://assets.hemmings.com/uimage/60207774-770-0@2X.jpg?rev=1", "https://assets.hemmings.com/uimage/60207775-770-0@2X.jpg?rev=1", "https://assets.hemmings.com/uimage/60207776-770-0@2X.jpg?rev=1"], "mileage": 200.0, "seller_name": "MJC Classic Cars", "title": "1966 Ford Mustang Coupe", "total_results": " 133", "price": "21500", "page_count": 9.0, "year": "1966", "href": "https://www.hemmings.com/classifieds/dealer/ford/mustang/2000962.html", "brand": "Ford", "reference_id": "2000962", "kilometers": 321.8, "model": "Mustang", "specs": {"Interior:": "Copper and Ivory", "Location:": "Lakeland, Florida,  33801", "description": ["The first Gen is the most desired of the generation of Mustangs.", "This beauty was restored to a high level two years ago and", "some dress up custom features added. Very high quality", "workmanship rarely seen in a car at this price point.", "Now it is ready for its new owner.", "Very straight, original body panel car, ready to drive.", "High end Copper Metallic repaint with Ivory stripes. New Copper", "& Ivory  Pony bucket seat interior. New door panels, new carpet", "and headliner. New dash, gauges & console. All new chrome", "and stainless trim. Excellent cosmetics.", "Vintage air conditioning added on restoration", "Rebuilt straight inline six cylinder engine.", "Factory three speed manual transmission", "Split exhaust manifolds and dual exhaust", "New wheel covers and new white letter radial tires", "BOLD FACT:", "DRESSED UP - HIGH END RESTORATION", "FACTS:", "Accident free & rust free original sheet metal", "High end repaint in Copper Metallic - Ivory stripes", "Mint new Copper & Ivory Pony bucket seat interior", "Refreshed dash, new carpet, top & door panels", "New chrome and soft trim throughout", "Rebuilt straight six engine", "Three speed manual transmission", "New AM/FM radio and speakers", "New wheel covers and new radial tires", "Check out our full inventory at www.MJCClassicCars.com"], "Exterior:": "copper metallic", "Condition:": "Excellent", "Transmission:": "Manual", "Mileage:": "200"}},
{"src": ["https://assets.hemmings.com/uimage/60126192-770-0@2X.jpg?rev=1", "https://assets.hemmings.com/uimage/60126195-770-0@2X.jpg?rev=1", "https://assets.hemmings.com/uimage/60126188-770-0@2X.jpg?rev=1", "https://assets.hemmings.com/uimage/60126200-770-0@2X.jpg?rev=1", "https://assets.hemmings.com/uimage/60126193-770-0@2X.jpg?rev=1", "https://assets.hemmings.com/uimage/60126187-770-0@2X.jpg?rev=1", "https://assets.hemmings.com/uimage/60126203-770-0@2X.jpg?rev=1", "https://assets.hemmings.com/uimage/60126190-770-0@2X.jpg?rev=1", "https://assets.hemmings.com/uimage/60126194-770-0@2X.jpg?rev=1", "https://assets.hemmings.com/uimage/60126197-770-0@2X.jpg?rev=1", "https://assets.hemmings.com/uimage/60126198-770-0@2X.jpg?rev=1", "https://assets.hemmings.com/uimage/60126205-770-0@2X.jpg?rev=1", "https://assets.hemmings.com/uimage/60126207-770-0@2X.jpg?rev=1", "https://assets.hemmings.com/uimage/60126191-770-0@2X.jpg?rev=1", "https://assets.hemmings.com/uimage/60126189-770-0@2X.jpg?rev=1", "https://assets.hemmings.com/uimage/60126199-770-0@2X.jpg?rev=1", "https://assets.hemmings.com/uimage/60126222-770-0@2X.jpg?rev=1", "https://assets.hemmings.com/uimage/60126202-770-0@2X.jpg?rev=1", "https://assets.hemmings.com/uimage/60126201-770-0@2X.jpg?rev=1", "https://assets.hemmings.com/uimage/60126196-770-0@2X.jpg?rev=1", "https://assets.hemmings.com/uimage/60126204-770-0@2X.jpg?rev=1", "https://assets.hemmings.com/uimage/60126181-770-0@2X.jpg?rev=1", "https://assets.hemmings.com/uimage/60126175-770-0@2X.jpg?rev=1", "https://assets.hemmings.com/uimage/60126182-770-0@2X.jpg?rev=1", "https://assets.hemmings.com/uimage/60126186-770-0@2X.jpg?rev=1", "https://assets.hemmings.com/uimage/60126176-770-0@2X.jpg?rev=1", "https://assets.hemmings.com/uimage/60126218-770-0@2X.jpg?rev=1", "https://assets.hemmings.com/uimage/60126178-770-0@2X.jpg?rev=1", "https://assets.hemmings.com/uimage/60126180-770-0@2X.jpg?rev=1", "https://assets.hemmings.com/uimage/60126179-770-0@2X.jpg?rev=1", "https://assets.hemmings.com/uimage/60126183-770-0@2X.jpg?rev=1", "https://assets.hemmings.com/uimage/60126184-770-0@2X.jpg?rev=1", "https://assets.hemmings.com/uimage/60126185-770-0@2X.jpg?rev=1", "https://assets.hemmings.com/uimage/60126177-770-0@2X.jpg?rev=1", "https://assets.hemmings.com/uimage/60126213-770-0@2X.jpg?rev=1", "https://assets.hemmings.com/uimage/60126211-770-0@2X.jpg?rev=1", "https://assets.hemmings.com/uimage/60126206-770-0@2X.jpg?rev=1", "https://assets.hemmings.com/uimage/60126223-770-0@2X.jpg?rev=1", "https://assets.hemmings.com/uimage/60126208-770-0@2X.jpg?rev=1", "https://assets.hemmings.com/uimage/60126209-770-0@2X.jpg?rev=1", "https://assets.hemmings.com/uimage/60126215-770-0@2X.jpg?rev=1", "https://assets.hemmings.com/uimage/60126216-770-0@2X.jpg?rev=1", "https://assets.hemmings.com/uimage/60126217-770-0@2X.jpg?rev=1", "https://assets.hemmings.com/uimage/60126210-770-0@2X.jpg?rev=1", "https://assets.hemmings.com/uimage/60126219-770-0@2X.jpg?rev=1", "https://assets.hemmings.com/uimage/60126220-770-0@2X.jpg?rev=1"], "mileage": 87339.0, "seller_name": "Milford Auto Sales", "title": "1965 Ford Mustang Fastback", "total_results": " 133", "price": "21900", "page_count": 9.0, "year": "1965", "href": "https://www.hemmings.com/classifieds/dealer/ford/mustang/1996470.html", "brand": "Ford", "reference_id": "1996470", "kilometers": 140528.451, "model": "Mustang", "specs": {"Interior:": "Black", "Location:": "Hopedale, Massachusetts,  01747", "description": ["1965 FORD MUSTANG FASTBACK", "200 CI 6 CYL \"T\" CODE.. 3 SPEED MANUAL TRANSMISSION", "THIS 65 MUSTANG FASTBACK WAS PURCHASED OUT OF TEXAS IN 2016. THE PAST OWNER HAD THIS CAR COMPLETELY RESTORED. BEING FROM TEXAS THE BODY WAS PRETTY GOOD TO START WITH.", "DURING THE LAST YEAR OVER $20,000 WAS SPENT ON THE RESTORATION, NOT INCLUDING THE COST OF THE CAR.. WITH A TON OF NEW PARTS INCLUDING; NEW FRONT & REAR BUMPERS, FRONT & REAR VALANCE PANELS, BACK UP LIGHTS, EMBLEMS, BRAKE COMPONENTS, TUNE UP PARTS, FUEL TANK, INTERIOR, ETC..", "THE BODY ON THIS 65 MUSTANG FASTBACK IS VERY STRAIGHT AND THE RANGOON RED PAINT IS KILLER.. VINTAGE KEYSTONES WHEELS WITH BRAND NEW RADIAL TIRES LOOK GREAT.. THE BLACK BUCKET SEAT INTERIOR IS EXTREMELY NICE. EQUIPPED FOLD DOWN REAR SEAT, AM/FM CASSETTE STEREO, CORRECT SHIFTER AND WORKING UNDER DASH A/C..", "THE ORIGINAL 200 6CYL ENGINE RUNS WELL, THE ENGINE BAY IS DETAILED NICELY, A VINTAGE A/C COMPRESSOR IS MOUNTED DOWN LOW. THIS MUSTANG DRIVES VERY GOOD..", "$21900   508 269 8878"], "Exterior:": "Rangoon Red", "Condition:": "Excellent", "Transmission:": "Manual", "Mileage:": "87339"}},
{"src": ["https://assets.hemmings.com/uimage/60127370-770-0@2X.jpg?rev=1", "https://assets.hemmings.com/uimage/60127325-770-0@2X.jpg?rev=1", "https://assets.hemmings.com/uimage/60127631-770-0@2X.jpg?rev=1", "https://assets.hemmings.com/uimage/60127373-770-0@2X.jpg?rev=1", "https://assets.hemmings.com/uimage/60127432-770-0@2X.jpg?rev=1", "https://assets.hemmings.com/uimage/60127458-770-0@2X.jpg?rev=1", "https://assets.hemmings.com/uimage/60127409-770-0@2X.jpg?rev=1", "https://assets.hemmings.com/uimage/60127520-770-0@2X.jpg?rev=1", "https://assets.hemmings.com/uimage/60127476-770-0@2X.jpg?rev=1", "https://assets.hemmings.com/uimage/60127491-770-0@2X.jpg?rev=1", "https://assets.hemmings.com/uimage/60127540-770-0@2X.jpg?rev=1", "https://assets.hemmings.com/uimage/60127567-770-0@2X.jpg?rev=1", "https://assets.hemmings.com/uimage/60127591-770-0@2X.jpg?rev=1", "https://assets.hemmings.com/uimage/60127603-770-0@2X.jpg?rev=1", "https://assets.hemmings.com/uimage/60127619-770-0@2X.jpg?rev=1", "https://assets.hemmings.com/uimage/60127624-770-0@2X.jpg?rev=1", "https://assets.hemmings.com/uimage/60127626-770-0@2X.jpg?rev=1", "https://assets.hemmings.com/uimage/60127629-770-0@2X.jpg?rev=1", "https://assets.hemmings.com/uimage/60127297-770-0@2X.jpg?rev=1"], "mileage": "", "seller_name": null, "title": "1965 Ford Mustang for Sale", "total_results": " 133", "price": "18750", "page_count": 9.0, "year": "1965", "href": "https://www.hemmings.com/classifieds/cars-for-sale/ford/mustang/1996586.html", "brand": "Ford", "reference_id": "1996586", "kilometers": "", "model": "Mustang", "specs": {"Interior:": "White Pearl", "Location:": "Dallas, Georgia,  30157", "description": ["Selling our breathtakingly gorgeous Original 289 V8 Mustang!\rShe has always been an incredible fun ride, and the brand new double exhaust system has added a goosebumps guarantee. This Mustang has been restored with love and detail. \r\rNew Paint \rNew Interior \rNew Fuel Tank \rNew Brake work all around \rNew starter \rNew Belts and filters \rNew back Tires \rNew some Joint work \rNew front and back Window and seals\rShe runs strong and smooth, with a very enjoyable factory suspension work. Engine has been intentionally left as original as possible.\r\rIt has a underdash A/C system that will turn on when hooked up, but it will need some work to run as it should. Power steering has been disconnected, but the PS system is still installed.\r\rDriving the Mustang with the new and bigger steering wheel is absolutely sufficient, and ads a very good feel to the road.\r\rIt's our weekend driver and it will add allot of joy to the next owners life, for sure!"], "Exterior:": "Blue Metallic", "Condition:": "Excellent", "Transmission:": "Auto"}},
{"src": ["https://assets.hemmings.com/uimage/60117818-770-0@2X.jpg?rev=1", "https://assets.hemmings.com/uimage/60117232-770-0@2X.jpg?rev=1", "https://assets.hemmings.com/uimage/60117226-770-0@2X.jpg?rev=1", "https://assets.hemmings.com/uimage/60117229-770-0@2X.jpg?rev=1", "https://assets.hemmings.com/uimage/60117255-770-0@2X.jpg?rev=1", "https://assets.hemmings.com/uimage/60117220-770-0@2X.jpg?rev=1", "https://assets.hemmings.com/uimage/60117254-770-0@2X.jpg?rev=1", "https://assets.hemmings.com/uimage/60117236-770-0@2X.jpg?rev=1", "https://assets.hemmings.com/uimage/60117257-770-0@2X.jpg?rev=1", "https://assets.hemmings.com/uimage/60117230-770-0@2X.jpg?rev=1", "https://assets.hemmings.com/uimage/60117231-770-0@2X.jpg?rev=1", "https://assets.hemmings.com/uimage/60117228-770-0@2X.jpg?rev=1", "https://assets.hemmings.com/uimage/60117253-770-0@2X.jpg?rev=1", "https://assets.hemmings.com/uimage/60117241-770-0@2X.jpg?rev=1", "https://assets.hemmings.com/uimage/60117234-770-0@2X.jpg?rev=1", "https://assets.hemmings.com/uimage/60117239-770-0@2X.jpg?rev=1", "https://assets.hemmings.com/uimage/60117240-770-0@2X.jpg?rev=1", "https://assets.hemmings.com/uimage/60117249-770-0@2X.jpg?rev=1", "https://assets.hemmings.com/uimage/60117252-770-0@2X.jpg?rev=1", "https://assets.hemmings.com/uimage/60117248-770-0@2X.jpg?rev=1", "https://assets.hemmings.com/uimage/60117251-770-0@2X.jpg?rev=1", "https://assets.hemmings.com/uimage/60117266-770-0@2X.jpg?rev=1", "https://assets.hemmings.com/uimage/60117256-770-0@2X.jpg?rev=1", "https://assets.hemmings.com/uimage/60117246-770-0@2X.jpg?rev=1", "https://assets.hemmings.com/uimage/60117247-770-0@2X.jpg?rev=1", "https://assets.hemmings.com/uimage/60117243-770-0@2X.jpg?rev=1", "https://assets.hemmings.com/uimage/60117250-770-0@2X.jpg?rev=1", "https://assets.hemmings.com/uimage/60117258-770-0@2X.jpg?rev=1", "https://assets.hemmings.com/uimage/60117244-770-0@2X.jpg?rev=1", "https://assets.hemmings.com/uimage/60117262-770-0@2X.jpg?rev=1", "https://assets.hemmings.com/uimage/60117259-770-0@2X.jpg?rev=1", "https://assets.hemmings.com/uimage/60117261-770-0@2X.jpg?rev=1", "https://assets.hemmings.com/uimage/60117264-770-0@2X.jpg?rev=1", "https://assets.hemmings.com/uimage/60117265-770-0@2X.jpg?rev=1", "https://assets.hemmings.com/uimage/60117238-770-0@2X.jpg?rev=1", "https://assets.hemmings.com/uimage/60117269-770-0@2X.jpg?rev=1", "https://assets.hemmings.com/uimage/60117268-770-0@2X.jpg?rev=1", "https://assets.hemmings.com/uimage/60117267-770-0@2X.jpg?rev=1"], "mileage": 4421.0, "seller_name": "Milford Auto Sales", "title": "1966 Ford Mustang Coupe", "total_results": " 133", "price": "19900", "page_count": 9.0, "year": "1966", "href": "https://www.hemmings.com/classifieds/dealer/ford/mustang/1995861.html", "brand": "Ford", "reference_id": "1995861", "kilometers": 7113.389, "model": "Mustang", "specs": {"Interior:": "Parchment", "Location:": "Hopedale, Massachusetts,  01747", "description": ["1966 FORD MUSTANG COUPE", "289 CI V8 \"C\" CODE.. C4 AUTOMATIC TRANS. CALIFORNIA BUILT AND CALIFORNIA TITLED.", "THE CURRENT CA. TITLE READS 4391 ACTUAL MILES. ODOMETER CURRENTLY SHOWS 4461", "THIS IS WHAT WE LEARNED ABOUT THIS SPECIAL MUSTANG.. THIS SUPER CLEAN MUSTANG WAS PUT AWAY IN A DRY", "GARAGE SOMEWHERE IN THE LATE 60'S BY THE ORIGINAL OWNER.. AFTER HER PASSING THIS CAR WAS SOLD TO A FAMILY MEMBER IN 1994 WITH ONLY 4391 ACTUAL MILES.. IN 2006 THIS MUSTANG WAS FINALLY REMOVED FROM ITS LONG TERM STORAGE AND SHIPPED OUT EAST..", "THE CAR HELD UP WELL OVER THE YEARS BUT THE PAINT WAS WEAK.. THIS MUSTANG WAS TREATED TO A HIGH QUALITY REPAINT IN 2006.. FINISHED IN ITS ORIGINAL COLOR OF ANTIQUE BRONZE METALLIC BASE CLEAR OVER A PIN STRAIGHT BODY. THE ORIGINAL FLOORS ARE INSANE.. THE RED OXIDE IS LIKE DAY ONE!! THE CHROME IS VERY NICE AS WELL AS THE BUMPERS.", "THE ORIGINAL 289 2BBL ENGINE STILL RETAINS THE FACTORY CALIFORNIA SMOG SYSTEM. ALSO EQUIPPED WITH POWER STEERING.. UNDER THE HOOD IS VERY CORRECT..", "THE PARCHMENT AND ROSETTE STANDARD INTERIOR IS JUST STUNNING.. FROM THE DOOR PANELS TO THE HEADLINER THE INTERIOR SHOWS VERY WELL. A SANYO STEREO WAS ADDED IN THE 90'S.", "THIS 66 MUSTANG COUPE RUNS SUPER NICE AND DRIVES BETTER.. $19900   508 269 8878"], "Exterior:": "Antique Bronze", "Condition:": "Excellent", "Transmission:": "Auto", "Mileage:": "4421"}},
{"src": ["https://assets.hemmings.com/uimage/60112674-770-0@2X.jpg?rev=1", "https://assets.hemmings.com/uimage/60112673-770-0@2X.jpg?rev=1", "https://assets.hemmings.com/uimage/60112667-770-0@2X.jpg?rev=1", "https://assets.hemmings.com/uimage/60112670-770-0@2X.jpg?rev=1", "https://assets.hemmings.com/uimage/60112584-770-0@2X.jpg?rev=1", "https://assets.hemmings.com/uimage/60112586-770-0@2X.jpg?rev=1", "https://assets.hemmings.com/uimage/60112587-770-0@2X.jpg?rev=1", "https://assets.hemmings.com/uimage/60112588-770-0@2X.jpg?rev=1", "https://assets.hemmings.com/uimage/60112655-770-0@2X.jpg?rev=1", "https://assets.hemmings.com/uimage/60112653-770-0@2X.jpg?rev=1", "https://assets.hemmings.com/uimage/60112658-770-0@2X.jpg?rev=1", "https://assets.hemmings.com/uimage/60112660-770-0@2X.jpg?rev=1", "https://assets.hemmings.com/uimage/60112659-770-0@2X.jpg?rev=1", "https://assets.hemmings.com/uimage/60112643-770-0@2X.jpg?rev=1", "https://assets.hemmings.com/uimage/60112645-770-0@2X.jpg?rev=1", "https://assets.hemmings.com/uimage/60112590-770-0@2X.jpg?rev=1", "https://assets.hemmings.com/uimage/60112648-770-0@2X.jpg?rev=1", "https://assets.hemmings.com/uimage/60112629-770-0@2X.jpg?rev=1", "https://assets.hemmings.com/uimage/60112631-770-0@2X.jpg?rev=1", "https://assets.hemmings.com/uimage/60112628-770-0@2X.jpg?rev=1", "https://assets.hemmings.com/uimage/60112635-770-0@2X.jpg?rev=1", "https://assets.hemmings.com/uimage/60112640-770-0@2X.jpg?rev=1"], "mileage": "", "seller_name": null, "title": "1966 Ford Mustang for Sale", "total_results": " 133", "price": "30000", "page_count": 9.0, "year": "1966", "href": "https://www.hemmings.com/classifieds/cars-for-sale/ford/mustang/1995644.html", "brand": "Ford", "reference_id": "1995644", "kilometers": "", "model": "Mustang", "specs": {"Interior:": "Black", "Location:": "Gaylord , Michigan,  49735", "description": ["This is a prime example of a 1966 Mustang! It has a 347ci engine with all forged internals coupled to a C4 transmission, brand new American Racing Wheels, pony interior, new windshield, digital radio and a great sounding duel exhaust with chrome tips.  This car is all original sheet metal and as clean underneath as it is on top.  With led headlights and tail lights, along with an MSD ignition, this car was built to drive and will turn heads wherever it goes.  It has over $50,000 invested - no expense was spared and no part was overlooked. If you are in the market for an amazing Mustang that you can buy today and enjoy for years to come, look no further."], "Exterior:": "Dark red with silver stripes", "Condition:": "Mint", "Transmission:": "Auto"}},
{"src": ["https://assets.hemmings.com/uimage/59330060-770-0@2X.jpg?rev=1", "https://assets.hemmings.com/uimage/59330053-770-0@2X.jpg?rev=1", "https://assets.hemmings.com/uimage/59330052-770-0@2X.jpg?rev=1", "https://assets.hemmings.com/uimage/59330050-770-0@2X.jpg?rev=1", "https://assets.hemmings.com/uimage/59330051-770-0@2X.jpg?rev=1", "https://assets.hemmings.com/uimage/59330054-770-0@2X.jpg?rev=1", "https://assets.hemmings.com/uimage/59330055-770-0@2X.jpg?rev=1", "https://assets.hemmings.com/uimage/59330056-770-0@2X.jpg?rev=1", "https://assets.hemmings.com/uimage/59330058-770-0@2X.jpg?rev=1", "https://assets.hemmings.com/uimage/59330057-770-0@2X.jpg?rev=1", "https://assets.hemmings.com/uimage/59330048-770-0@2X.jpg?rev=1", "https://assets.hemmings.com/uimage/59330044-770-0@2X.jpg?rev=1", "https://assets.hemmings.com/uimage/59330043-770-0@2X.jpg?rev=1", "https://assets.hemmings.com/uimage/59330046-770-0@2X.jpg?rev=1", "https://assets.hemmings.com/uimage/59330049-770-0@2X.jpg?rev=1", "https://assets.hemmings.com/uimage/59330045-770-0@2X.jpg?rev=1", "https://assets.hemmings.com/uimage/59330042-770-0@2X.jpg?rev=1", "https://assets.hemmings.com/uimage/59330036-770-0@2X.jpg?rev=1", "https://assets.hemmings.com/uimage/59330037-770-0@2X.jpg?rev=1", "https://assets.hemmings.com/uimage/59330039-770-0@2X.jpg?rev=1", "https://assets.hemmings.com/uimage/59330038-770-0@2X.jpg?rev=1", "https://assets.hemmings.com/uimage/59330040-770-0@2X.jpg?rev=1", "https://assets.hemmings.com/uimage/59330041-770-0@2X.jpg?rev=1", "https://assets.hemmings.com/uimage/59330047-770-0@2X.jpg?rev=1", "https://assets.hemmings.com/uimage/59330035-770-0@2X.jpg?rev=1", "https://assets.hemmings.com/uimage/59330034-770-0@2X.jpg?rev=1", "https://assets.hemmings.com/uimage/59330059-770-0@2X.jpg?rev=1", "https://assets.hemmings.com/uimage/59330033-770-0@2X.jpg?rev=1"], "mileage": 21002.0, "seller_name": "Classic Motors of Washington DC", "title": "1965 Ford Mustang 289 Notchback", "total_results": " 133", "price": "18900", "page_count": 9.0, "year": "1965", "href": "https://www.hemmings.com/classifieds/dealer/ford/mustang/1955099.html", "brand": "Ford", "reference_id": "1955099", "kilometers": 33792.218, "model": "Mustang", "specs": {"Interior:": "Black", "Location:": "Washington, District of Columbia,  20016", "description": ["This is a beautiful 1965 Poppy Red Mustang Notchback. She's a 65' Notchback with a 289CU V8 engine with an automatic transmission. I've decoded the VIN number 5F07C634151. The 5 indications the year of production so this Mustang was produced in 1965, the F indicates the location where the car was manufactured in this instance it was made in Dearborn Michigan, the 07 means that the car original started its life out as a coupe 07=Hardtop. The Letter \"C\" in the Vin indicates  that the car is an original 289-2Y engine. The remaining numbers 634151 stand for the consecutive unit numbers. This car has the original 289 engine in it. The only thing that was changed was at some point the manifold and carburetor were changed from the standard two barrel to a four barrel Edelbrock which makes the car faster and more drivable the four barrel adds additional horsepower. This car comes with a very detailed service history. I have several hard copies of service records spanning a number of years, which is great but it shows how well the owner has treated this mustang. Anytime the car's needed service it has been done from ball joints and suspension to fluid and oil changes.. The interior is virtually flawless with no cracks in the dash or seats. This beautiful Poppy Red 289 1965 Mustang is available for sale today and will surely make its next owner very happy."], "Exterior:": "Red", "Condition:": "Excellent", "Transmission:": "Auto", "Mileage:": "21002"}},
{"src": ["https://assets.hemmings.com/uimage/60468793-770-0@2X.jpg?rev=21", "https://assets.hemmings.com/uimage/60468794-770-0@2X.jpg?rev=21", "https://assets.hemmings.com/uimage/60468798-770-0@2X.jpg?rev=21", "https://assets.hemmings.com/uimage/60468801-770-0@2X.jpg?rev=21", "https://assets.hemmings.com/uimage/60468806-770-0@2X.jpg?rev=21", "https://assets.hemmings.com/uimage/60468808-770-0@2X.jpg?rev=21", "https://assets.hemmings.com/uimage/60468811-770-0@2X.jpg?rev=21", "https://assets.hemmings.com/uimage/60468813-770-0@2X.jpg?rev=21", "https://assets.hemmings.com/uimage/60468816-770-0@2X.jpg?rev=21", "https://assets.hemmings.com/uimage/60468819-770-0@2X.jpg?rev=21", "https://assets.hemmings.com/uimage/60468821-770-0@2X.jpg?rev=21", "https://assets.hemmings.com/uimage/60468822-770-0@2X.jpg?rev=21", "https://assets.hemmings.com/uimage/60468825-770-0@2X.jpg?rev=21", "https://assets.hemmings.com/uimage/60468829-770-0@2X.jpg?rev=21", "https://assets.hemmings.com/uimage/60468833-770-0@2X.jpg?rev=21", "https://assets.hemmings.com/uimage/60468836-770-0@2X.jpg?rev=21", "https://assets.hemmings.com/uimage/60468838-770-0@2X.jpg?rev=21", "https://assets.hemmings.com/uimage/60468841-770-0@2X.jpg?rev=21", "https://assets.hemmings.com/uimage/60468844-770-0@2X.jpg?rev=21", "https://assets.hemmings.com/uimage/60468847-770-0@2X.jpg?rev=21", "https://assets.hemmings.com/uimage/60468850-770-0@2X.jpg?rev=21", "https://assets.hemmings.com/uimage/60468853-770-0@2X.jpg?rev=21", "https://assets.hemmings.com/uimage/60468855-770-0@2X.jpg?rev=21", "https://assets.hemmings.com/uimage/60468858-770-0@2X.jpg?rev=21", "https://assets.hemmings.com/uimage/60468860-770-0@2X.jpg?rev=21", "https://assets.hemmings.com/uimage/60468862-770-0@2X.jpg?rev=21", "https://assets.hemmings.com/uimage/60468867-770-0@2X.jpg?rev=21", "https://assets.hemmings.com/uimage/60468868-770-0@2X.jpg?rev=21", "https://assets.hemmings.com/uimage/60468870-770-0@2X.jpg?rev=21", "https://assets.hemmings.com/uimage/60468873-770-0@2X.jpg?rev=21", "https://assets.hemmings.com/uimage/60468876-770-0@2X.jpg?rev=21", "https://assets.hemmings.com/uimage/60468879-770-0@2X.jpg?rev=21", "https://assets.hemmings.com/uimage/60468884-770-0@2X.jpg?rev=21", "https://assets.hemmings.com/uimage/60468885-770-0@2X.jpg?rev=21", "https://assets.hemmings.com/uimage/60468887-770-0@2X.jpg?rev=21", "https://assets.hemmings.com/uimage/60468892-770-0@2X.jpg?rev=21", "https://assets.hemmings.com/uimage/60468894-770-0@2X.jpg?rev=21", "https://assets.hemmings.com/uimage/60468897-770-0@2X.jpg?rev=21", "https://assets.hemmings.com/uimage/60468899-770-0@2X.jpg?rev=21", "https://assets.hemmings.com/uimage/60468900-770-0@2X.jpg?rev=21", "https://assets.hemmings.com/uimage/60468903-770-0@2X.jpg?rev=21", "https://assets.hemmings.com/uimage/60468905-770-0@2X.jpg?rev=21", "https://assets.hemmings.com/uimage/60468907-770-0@2X.jpg?rev=21", "https://assets.hemmings.com/uimage/60468910-770-0@2X.jpg?rev=21", "https://assets.hemmings.com/uimage/60468912-770-0@2X.jpg?rev=21", "https://assets.hemmings.com/uimage/60468917-770-0@2X.jpg?rev=21", "https://assets.hemmings.com/uimage/60468920-770-0@2X.jpg?rev=21", "https://assets.hemmings.com/uimage/60468922-770-0@2X.jpg?rev=21", "https://assets.hemmings.com/uimage/60468925-770-0@2X.jpg?rev=21", "https://assets.hemmings.com/uimage/60468928-770-0@2X.jpg?rev=21"], "mileage": 57807.0, "seller_name": "Streetside Classics - Tampa", "title": "1965 Ford Mustang for Sale", "total_results": " 133", "price": "27995", "page_count": 9.0, "year": "1965", "href": "https://www.hemmings.com/classifieds/dealer/ford/mustang/1996642.html", "brand": "Ford", "reference_id": "1996642", "kilometers": 93011.463, "model": "Mustang", "specs": {"Interior:": "Cream", "Location:": "Lutz, Florida,  33559", "description": ["With a V8, A/C, and sunning red paint, it's time for you to get your hands on your dream 1965 Ford Mustang for quite a nice price.", "The color of this coupe makes it the perfect standout.  A first-year Mustang dressed in red is iconic, but when you render it in a deeper shade of Black Cherry, it gets extra attention when hanging out with the other classics. No matter if you are across the show field or one-inch away, the investment in this color is instantly apparent.  There's a deep luster and the kind of hard shine that makes it look like this coupe has a top coat made of glass.  To pull off this presentation, you also need super straight body panels.  The total effect gives the first-year Mustang's crisp lines a more sophisticated appearance.  That's backed up by the full trim package, including new bumpers and grille to keep everything shining at its best.  Even the bright of the 14-inch styled steel wheels give this one the kind of distinction you're looking for when you want to stand out from the crowd.", "Inside the theme of an upgraded classic presentation continues with the two-tone interior.  The white vinyl seats look great, and they just seem to reinforce the clean presentation of this car.  Plus, the carpets are black so you never have to worry about taking your shoes off before hopping in and going for a drive... and that's exactly what this car was built to do.  It has all the right upgrades to keep everyone happy, including the cup holder center console, AM/FM stereo, and R134a air conditioning.  It all makes for a classic cruiser that's comfortable enough for even the daily commute.", "Ford's reliable and perky 289 cubic-inch V8 moves the lightweight Mustang enthusiastically through any traffic \u2013 especially with the addition of a four-barrel carburetor on top. The engine bay has all the right style upgrades like the bright intake, valve covers, bracer bar, and air topper. There was even a Monte Carlo bar added for extra rigidity and flair.  These motors are extremely reliable, parts are readily available, and performance is very good \u2013 all of which gives you an underlying feeling of carefree classic motoring.  Adding to this go-anywhere sensation in this the three-speed automatic transmission and the modern grip of Hankook Optimo tires.", "Complete with build receipts and maintenance records, the first-generation Ford Mustang is a true classic car for those who like driving.  Add in the stellar presentation, and you soon realize that vintage style distinction can be quite affordable. Don't miss out, call today!"], "Exterior:": "Black Cherry", "Transmission:": "Auto", "Mileage:": "57807"}},
{"src": ["https://assets.hemmings.com/uimage/60100662-770-0@2X.jpg?rev=1", "https://assets.hemmings.com/uimage/60100663-770-0@2X.jpg?rev=1", "https://assets.hemmings.com/uimage/60100664-770-0@2X.jpg?rev=1", "https://assets.hemmings.com/uimage/60100665-770-0@2X.jpg?rev=1", "https://assets.hemmings.com/uimage/60100666-770-0@2X.jpg?rev=1", "https://assets.hemmings.com/uimage/60100667-770-0@2X.jpg?rev=1", "https://assets.hemmings.com/uimage/60100668-770-0@2X.jpg?rev=1", "https://assets.hemmings.com/uimage/60100669-770-0@2X.jpg?rev=1", "https://assets.hemmings.com/uimage/60100670-770-0@2X.jpg?rev=1", "https://assets.hemmings.com/uimage/60100671-770-0@2X.jpg?rev=1", "https://assets.hemmings.com/uimage/60100672-770-0@2X.jpg?rev=1", "https://assets.hemmings.com/uimage/60100673-770-0@2X.jpg?rev=1", "https://assets.hemmings.com/uimage/60100674-770-0@2X.jpg?rev=1", "https://assets.hemmings.com/uimage/60100675-770-0@2X.jpg?rev=1", "https://assets.hemmings.com/uimage/60100676-770-0@2X.jpg?rev=1", "https://assets.hemmings.com/uimage/60100677-770-0@2X.jpg?rev=1", "https://assets.hemmings.com/uimage/60100678-770-0@2X.jpg?rev=1", "https://assets.hemmings.com/uimage/60100679-770-0@2X.jpg?rev=1", "https://assets.hemmings.com/uimage/60100680-770-0@2X.jpg?rev=1", "https://assets.hemmings.com/uimage/60100681-770-0@2X.jpg?rev=1", "https://assets.hemmings.com/uimage/60100682-770-0@2X.jpg?rev=1", "https://assets.hemmings.com/uimage/60100683-770-0@2X.jpg?rev=1", "https://assets.hemmings.com/uimage/60100684-770-0@2X.jpg?rev=1", "https://assets.hemmings.com/uimage/60100685-770-0@2X.jpg?rev=1", "https://assets.hemmings.com/uimage/60100686-770-0@2X.jpg?rev=1", "https://assets.hemmings.com/uimage/60100687-770-0@2X.jpg?rev=1", "https://assets.hemmings.com/uimage/60100688-770-0@2X.jpg?rev=1", "https://assets.hemmings.com/uimage/60100689-770-0@2X.jpg?rev=1", "https://assets.hemmings.com/uimage/60100690-770-0@2X.jpg?rev=1", "https://assets.hemmings.com/uimage/60100691-770-0@2X.jpg?rev=1", "https://assets.hemmings.com/uimage/60100692-770-0@2X.jpg?rev=1", "https://assets.hemmings.com/uimage/60100693-770-0@2X.jpg?rev=1", "https://assets.hemmings.com/uimage/60100694-770-0@2X.jpg?rev=1", "https://assets.hemmings.com/uimage/60100695-770-0@2X.jpg?rev=1", "https://assets.hemmings.com/uimage/60100696-770-0@2X.jpg?rev=1"], "mileage": "", "seller_name": null, "title": "1964 Ford Mustang for Sale", "total_results": " 133", "price": "24500", "page_count": 9.0, "year": "1964", "href": "https://www.hemmings.com/classifieds/cars-for-sale/ford/mustang/1995025.html", "brand": "Ford", "reference_id": "1995025", "kilometers": "", "model": "Mustang", "specs": {"Interior:": "Palomino", "Location:": "Vale, North Carolina,  28168", "description": ["This one owner highly documented 1964 \u00bd Mustang was ordered new from Segal Ford in Stockton, CA and was delivered to Mr. Lou Ives of Stockton, CA on July 6, 1964.", "It is factory equipped with a 260 CI V8 engine, 3 speed manual, console, AM radio and air conditioning.  The no expense spared restoration took place a little over 6 years ago and still looks and drives like it is factory fresh.  The original color of Prairie Bronze was flawlessly applied and really looks sharp with the Palomino interior.   As you would expect with this high level of restoration, everything works as Ford intended along with the original AM radio and factory A/C.  What a pleasure to drive and can be driven any where any time with confidence.  Sale of this time capsule includes the original purchase order, personal checks for deposit and purchase, copy of original window sticker, 1964 California new vehicle registration, copies of titles, original keys and over $33,000 in restoration receipts.", "Door Plate", "Body 65A \u2013 Hard Top Standard Seats", "Color P \u2013 Prairie Bronze", "Trim 89 \u2013 Palomino Vinyl \u2013 Palomino Trim", "Date 19F \u2013 19th day of June", "DSO 72 \u2013 San Jose, CA", "Axel 1 \u2013 3:00 \u2013 1", "Trans 1 \u2013 3 Speed Manual", "Vehicle Warranty Number", "5 \u2013 64 \u2013 65", "F \u2013 Dearborn Assembly Plant", "07 \u2013 Coupe", "F \u2013 260 V8 (1964 \u00bd Mustang Only)", "172053 \u2013 Consecutive Unit Number", "Motor Cast Date", "4 \u2013 1964", "P \u2013 February", "24 \u2013 24th Day", "Motor Cast Number", "C \u2013 1960", "4 \u2013 Year of Decade (1964)", "0 \u2013 Generic Mode Design", "6015 \u2013 Engine Base Assembly", "B \u2013 First Revision to Design Change", "Transmission", "HEF BB \u2013 1964 260 CI Mustang Type 3.03", "4 E 13 \u2013 1964 May 13", "Rear End", "4 F 12 \u2013 1964 June 12", "If you have been looking for a highly restored 1964 \u00bd Mustang that has the documents to prove itself, you need to consider this one.", "$24,500 OBO", "Trades Considered"], "Exterior:": "Prairie Bronze", "Condition:": "Excellent", "Transmission:": "Manual"}},
{"src": ["https://assets.hemmings.com/uimage/60157494-770-0@2X.jpg?rev=1", "https://assets.hemmings.com/uimage/60157495-770-0@2X.jpg?rev=1", "https://assets.hemmings.com/uimage/60157492-770-0@2X.jpg?rev=1", "https://assets.hemmings.com/uimage/60157491-770-0@2X.jpg?rev=1", "https://assets.hemmings.com/uimage/60157499-770-0@2X.jpg?rev=1", "https://assets.hemmings.com/uimage/60157500-770-0@2X.jpg?rev=1", "https://assets.hemmings.com/uimage/60157496-770-0@2X.jpg?rev=1", "https://assets.hemmings.com/uimage/60157497-770-0@2X.jpg?rev=1", "https://assets.hemmings.com/uimage/60157456-770-0@2X.jpg?rev=1", "https://assets.hemmings.com/uimage/60157457-770-0@2X.jpg?rev=1", "https://assets.hemmings.com/uimage/60157460-770-0@2X.jpg?rev=1"], "mileage": 66022.0, "seller_name": null, "title": "1966 Ford Mustang GT", "total_results": " 133", "price": "26700", "page_count": 9.0, "year": "1966", "href": "https://www.hemmings.com/classifieds/cars-for-sale/ford/mustang/1998558.html", "brand": "Ford", "reference_id": "1998558", "kilometers": 106229.398, "model": "Mustang", "specs": {"Interior:": "Tahoe Turquoise/white", "Location:": "Fort Bragg, California,  95437", "description": ["This automobile is an authentic GT and has a stout 289 engine and 4-speed transmission. Factory air conditioning, AM radio, rally-pac gauges, rims, deluxe pony upholstery and more. Chrome is in excellent condition. Paint has a couple of flaws at close look. Always garaged, in barn shown, since pride ownership and is in the same condition when purchased 12 years ago."], "Exterior:": "Tahoe Turquoise/white vinyl top", "Condition:": "Excellent", "Transmission:": "Manual", "Mileage:": "66022"}},
{"src": ["https://assets.hemmings.com/uimage/55781378-770-0@2X.jpg?rev=1", "https://assets.hemmings.com/uimage/55781368-770-0@2X.jpg?rev=1", "https://assets.hemmings.com/uimage/55781369-770-0@2X.jpg?rev=1", "https://assets.hemmings.com/uimage/55781372-770-0@2X.jpg?rev=1", "https://assets.hemmings.com/uimage/55781371-770-0@2X.jpg?rev=1", "https://assets.hemmings.com/uimage/55781374-770-0@2X.jpg?rev=1", "https://assets.hemmings.com/uimage/55781375-770-0@2X.jpg?rev=1", "https://assets.hemmings.com/uimage/55781377-770-0@2X.jpg?rev=1", "https://assets.hemmings.com/uimage/55781373-770-0@2X.jpg?rev=1", "https://assets.hemmings.com/uimage/55781380-770-0@2X.jpg?rev=1", "https://assets.hemmings.com/uimage/55582979-770-0@2X.jpg?rev=1", "https://assets.hemmings.com/uimage/55781414-770-0@2X.jpg?rev=1", "https://assets.hemmings.com/uimage/55583298-770-0@2X.jpg?rev=1", "https://assets.hemmings.com/uimage/55781418-770-0@2X.jpg?rev=1", "https://assets.hemmings.com/uimage/55783428-770-0@2X.jpg?rev=1", "https://assets.hemmings.com/uimage/55783429-770-0@2X.jpg?rev=1", "https://assets.hemmings.com/uimage/55583297-770-0@2X.jpg?rev=1", "https://assets.hemmings.com/uimage/55781421-770-0@2X.jpg?rev=1", "https://assets.hemmings.com/uimage/55583001-770-0@2X.jpg?rev=1", "https://assets.hemmings.com/uimage/55781426-770-0@2X.jpg?rev=1", "https://assets.hemmings.com/uimage/55781430-770-0@2X.jpg?rev=1", "https://assets.hemmings.com/uimage/55781403-770-0@2X.jpg?rev=1", "https://assets.hemmings.com/uimage/55781398-770-0@2X.jpg?rev=1", "https://assets.hemmings.com/uimage/55781394-770-0@2X.jpg?rev=1", "https://assets.hemmings.com/uimage/55781389-770-0@2X.jpg?rev=1", "https://assets.hemmings.com/uimage/55781457-770-0@2X.jpg?rev=1", "https://assets.hemmings.com/uimage/55781436-770-0@2X.jpg?rev=1", "https://assets.hemmings.com/uimage/55781460-770-0@2X.jpg?rev=1", "https://assets.hemmings.com/uimage/55781444-770-0@2X.jpg?rev=1", "https://assets.hemmings.com/uimage/55781449-770-0@2X.jpg?rev=1", "https://assets.hemmings.com/uimage/55781454-770-0@2X.jpg?rev=1", "https://assets.hemmings.com/uimage/55583072-770-0@2X.jpg?rev=1", "https://assets.hemmings.com/uimage/55583043-770-0@2X.jpg?rev=1", "https://assets.hemmings.com/uimage/55583356-770-0@2X.jpg?rev=1", "https://assets.hemmings.com/uimage/59640590-770-0@2X.jpg?rev=1", "https://assets.hemmings.com/uimage/59640591-770-0@2X.jpg?rev=1", "https://assets.hemmings.com/uimage/59640592-770-0@2X.jpg?rev=1", "https://assets.hemmings.com/uimage/59640593-770-0@2X.jpg?rev=1", "https://assets.hemmings.com/uimage/59640594-770-0@2X.jpg?rev=1", "https://assets.hemmings.com/uimage/59640595-770-0@2X.jpg?rev=1", "https://assets.hemmings.com/uimage/59640596-770-0@2X.jpg?rev=1", "https://assets.hemmings.com/uimage/59640597-770-0@2X.jpg?rev=1", "https://assets.hemmings.com/uimage/59640602-770-0@2X.jpg?rev=1", "https://assets.hemmings.com/uimage/59640603-770-0@2X.jpg?rev=1", "https://assets.hemmings.com/uimage/59640598-770-0@2X.jpg?rev=1", "https://assets.hemmings.com/uimage/59640599-770-0@2X.jpg?rev=1", "https://assets.hemmings.com/uimage/59640600-770-0@2X.jpg?rev=1", "https://assets.hemmings.com/uimage/59640601-770-0@2X.jpg?rev=1", "https://assets.hemmings.com/uimage/59640604-770-0@2X.jpg?rev=1", "https://assets.hemmings.com/uimage/59640606-770-0@2X.jpg?rev=1"], "mileage": 132000.0, "seller_name": null, "title": "1966 Ford Mustang Convertible 289 V8, 4 Barrel, 4 Speed", "total_results": " 133", "price": "24500", "page_count": 9.0, "year": "1966", "href": "https://www.hemmings.com/classifieds/cars-for-sale/ford/mustang/1852784.html", "brand": "Ford", "reference_id": "1852784", "kilometers": 212388.0, "model": "Mustang", "specs": {"Interior:": "Red Standard Interior", "Location:": "Mansfield, Massachusetts,  02048", "description": ["Fresh restoration,1966 matching numbers, Ford Mustang Convertible, Wimbledon White, Red Interior, Black Power top, new Red convertible boot, and matching red pin stripe around the coves. This beautiful Mustang convertible has a rebuilt original 289 V8, original 4 speed transmission and differential, 4 barrel Holley carburetor, new two inch dual exhaust, power steering, new power black convertible top, steel style wheels, new tires, and clutch. This pony has an excellent contrasting red standard interior, with new upholstered seats and restored seat belts.  This stunning car has less than 1k miles since being restored three years ago. All systems have been refreshed, or restored. For your listening pleasure there is a period looking new AM/FM stereo radio with speakers in the kick panels and dash.   Car runs great and you will be styling, driving this beautiful Mustang convertible. I have owned the car for 40 years and it is stored in a climate controlled garage, and never driven in the rain or snow. This gorgeous first generation Mustang looks just as nice underneath as on top, with no rust anywhere on this car. The car has a clean MA title, with registration MSTANG. If registering the in MA, the license plate is available with the car. Professionally restored by Motor Club Automotive of MA specializing in Mustangs.", "Price has just been reduce to $24,500. Please call or email for more information, additional videos and pictures,", "774 284 1212", ", or", "[Email Seller]", ".  You will not be disappointed."], "Exterior:": "Wimbledon White with Black Power top", "Condition:": "Excellent", "Transmission:": "Manual", "Mileage:": "132000"}},
{"src": ["https://assets.hemmings.com/uimage/60405758-770-0@2X.jpg?rev=22", "https://assets.hemmings.com/uimage/60405761-770-0@2X.jpg?rev=22", "https://assets.hemmings.com/uimage/60405763-770-0@2X.jpg?rev=22", "https://assets.hemmings.com/uimage/60405765-770-0@2X.jpg?rev=22", "https://assets.hemmings.com/uimage/60405768-770-0@2X.jpg?rev=22", "https://assets.hemmings.com/uimage/60405771-770-0@2X.jpg?rev=22", "https://assets.hemmings.com/uimage/60405773-770-0@2X.jpg?rev=22", "https://assets.hemmings.com/uimage/60405779-770-0@2X.jpg?rev=22", "https://assets.hemmings.com/uimage/60405782-770-0@2X.jpg?rev=22", "https://assets.hemmings.com/uimage/60405784-770-0@2X.jpg?rev=22", "https://assets.hemmings.com/uimage/60405788-770-0@2X.jpg?rev=22", "https://assets.hemmings.com/uimage/60405789-770-0@2X.jpg?rev=22", "https://assets.hemmings.com/uimage/60405791-770-0@2X.jpg?rev=22", "https://assets.hemmings.com/uimage/60405794-770-0@2X.jpg?rev=22", "https://assets.hemmings.com/uimage/60405797-770-0@2X.jpg?rev=22", "https://assets.hemmings.com/uimage/60405799-770-0@2X.jpg?rev=22", "https://assets.hemmings.com/uimage/60405801-770-0@2X.jpg?rev=22", "https://assets.hemmings.com/uimage/60405804-770-0@2X.jpg?rev=22", "https://assets.hemmings.com/uimage/60405808-770-0@2X.jpg?rev=22", "https://assets.hemmings.com/uimage/60405810-770-0@2X.jpg?rev=22", "https://assets.hemmings.com/uimage/60405812-770-0@2X.jpg?rev=22", "https://assets.hemmings.com/uimage/60405813-770-0@2X.jpg?rev=22", "https://assets.hemmings.com/uimage/60405815-770-0@2X.jpg?rev=22", "https://assets.hemmings.com/uimage/60405819-770-0@2X.jpg?rev=22", "https://assets.hemmings.com/uimage/60405821-770-0@2X.jpg?rev=22", "https://assets.hemmings.com/uimage/60405823-770-0@2X.jpg?rev=22", "https://assets.hemmings.com/uimage/60405826-770-0@2X.jpg?rev=22", "https://assets.hemmings.com/uimage/60405829-770-0@2X.jpg?rev=22", "https://assets.hemmings.com/uimage/60405832-770-0@2X.jpg?rev=22", "https://assets.hemmings.com/uimage/60405833-770-0@2X.jpg?rev=22", "https://assets.hemmings.com/uimage/60405835-770-0@2X.jpg?rev=22", "https://assets.hemmings.com/uimage/60405837-770-0@2X.jpg?rev=22", "https://assets.hemmings.com/uimage/60405839-770-0@2X.jpg?rev=22", "https://assets.hemmings.com/uimage/60405840-770-0@2X.jpg?rev=22", "https://assets.hemmings.com/uimage/60405841-770-0@2X.jpg?rev=22", "https://assets.hemmings.com/uimage/60405842-770-0@2X.jpg?rev=22", "https://assets.hemmings.com/uimage/60405845-770-0@2X.jpg?rev=22", "https://assets.hemmings.com/uimage/60405846-770-0@2X.jpg?rev=22", "https://assets.hemmings.com/uimage/60405847-770-0@2X.jpg?rev=22", "https://assets.hemmings.com/uimage/60405848-770-0@2X.jpg?rev=22", "https://assets.hemmings.com/uimage/60405850-770-0@2X.jpg?rev=22", "https://assets.hemmings.com/uimage/60405852-770-0@2X.jpg?rev=22", "https://assets.hemmings.com/uimage/60405854-770-0@2X.jpg?rev=22", "https://assets.hemmings.com/uimage/60405855-770-0@2X.jpg?rev=22", "https://assets.hemmings.com/uimage/60405857-770-0@2X.jpg?rev=22", "https://assets.hemmings.com/uimage/60405858-770-0@2X.jpg?rev=22", "https://assets.hemmings.com/uimage/60405859-770-0@2X.jpg?rev=22", "https://assets.hemmings.com/uimage/60405862-770-0@2X.jpg?rev=22", "https://assets.hemmings.com/uimage/60405863-770-0@2X.jpg?rev=22"], "mileage": 38746.0, "seller_name": "Old Forge Motorcars", "title": "1966 Ford Mustang for Sale", "total_results": " 133", "price": "16900", "page_count": 9.0, "year": "1966", "href": "https://www.hemmings.com/classifieds/dealer/ford/mustang/1998592.html", "brand": "Ford", "reference_id": "1998592", "kilometers": 62342.314, "model": "Mustang", "specs": {"Interior:": "Blue & White", "Location:": "Lansdale, Pennsylvania,  19446", "description": ["1966 FORD MUSTANG COUPE", "VIN  6F07C185197", "- 289 ''C'' CODE V8", "- AUTOMATIC", "- POWER STEERING", "- ALUMINUM RADIATOR", "- AIR CONDITIONING", "- BLUE EXTERIOR", "- BLUE/WHITE VINYL PONY INTERIOR", "- GT REAR VALANCE", "- STYLED STEEL WHEELS", "- AFTERMARKET 3RD BRAKE LIGHT", "- ODO  38749 MILES", "OLD FORGE Motorcars presents this 1966 Ford Mustang coupe.  The light blue paintwork is showing its age and has some issues on the driver side door and fender.  Overall the paint is in good condition.  The brightwork is in good condition.  The blue and white Pony interior is in very good shape except for some seam separation in the driver seat.  This Mustang is a good running and driving car that you can have lots of fun in.", "OLD FORGE ADVANTAGE:  Ask about our 120 Multi-point Inspection.  Our inspection has revealed some minor concerns that can be easily addressed.", "$16900", "CLOSE OFFERS CONSIDERED", "As with all the cars we offer, we encourage independent inspection.", "''WE ARE ALWAYS LOOKING FOR COLLECTOR CARS''", "PLEASE CHECK OUR 100% POSITIVE EBAY FEEDBACK AND BUY WITH CONFIDENCE"], "Exterior:": "Blue", "Condition:": "Excellent", "Transmission:": "Auto", "Mileage:": "38746"}},
{"src": ["https://assets.hemmings.com/uimage/60181562-770-0@2X.jpg?rev=1", "https://assets.hemmings.com/uimage/60181564-770-0@2X.jpg?rev=1", "https://assets.hemmings.com/uimage/60181567-770-0@2X.jpg?rev=1", "https://assets.hemmings.com/uimage/60181575-770-0@2X.jpg?rev=1", "https://assets.hemmings.com/uimage/60181570-770-0@2X.jpg?rev=1", "https://assets.hemmings.com/uimage/60181578-770-0@2X.jpg?rev=1", "https://assets.hemmings.com/uimage/60181581-770-0@2X.jpg?rev=1", "https://assets.hemmings.com/uimage/60181583-770-0@2X.jpg?rev=1", "https://assets.hemmings.com/uimage/60181586-770-0@2X.jpg?rev=1", "https://assets.hemmings.com/uimage/60181588-770-0@2X.jpg?rev=1", "https://assets.hemmings.com/uimage/60181590-770-0@2X.jpg?rev=1", "https://assets.hemmings.com/uimage/60181593-770-0@2X.jpg?rev=1", "https://assets.hemmings.com/uimage/60181594-770-0@2X.jpg?rev=1", "https://assets.hemmings.com/uimage/60181596-770-0@2X.jpg?rev=1", "https://assets.hemmings.com/uimage/60181599-770-0@2X.jpg?rev=1", "https://assets.hemmings.com/uimage/60181601-770-0@2X.jpg?rev=1", "https://assets.hemmings.com/uimage/60181604-770-0@2X.jpg?rev=1", "https://assets.hemmings.com/uimage/60181572-770-0@2X.jpg?rev=1"], "mileage": "", "seller_name": "Northwest Classic Auto Mall", "title": "1966 Ford Mustang for Sale", "total_results": " 133", "price": "24900", "page_count": 9.0, "year": "1966", "href": "https://www.hemmings.com/classifieds/dealer/ford/mustang/1999817.html", "brand": "Ford", "reference_id": "1999817", "kilometers": "", "model": "Mustang", "specs": {"Transmission:": "Auto", "Location:": "Medford, Oregon,  97502", "Condition:": "Excellent", "description": ["1968 Ford Mustang", "302 / Auto", "PS/PB,", "1970 302 Runs Excellent", "1970 Front Seats", "New:", "Interior complete", "Gas tank & lines", "Brakes - wheel cylinders and lines", "Wheels & tires", "Rear bumper", "Weatherstripping", "Radiator", "Very nice car to drive or show!", "If you are interested in this vehicle or have any questions,", "please call Bill at 541-779-1084 or 541-261-4213"]}},
{"src": ["https://assets.hemmings.com/uimage/60396464-770-0@2X.jpg?rev=21", "https://assets.hemmings.com/uimage/60396465-770-0@2X.jpg?rev=21", "https://assets.hemmings.com/uimage/60396466-770-0@2X.jpg?rev=21", "https://assets.hemmings.com/uimage/60396467-770-0@2X.jpg?rev=21", "https://assets.hemmings.com/uimage/60396468-770-0@2X.jpg?rev=21", "https://assets.hemmings.com/uimage/60396469-770-0@2X.jpg?rev=21", "https://assets.hemmings.com/uimage/60396470-770-0@2X.jpg?rev=21", "https://assets.hemmings.com/uimage/60396471-770-0@2X.jpg?rev=21", "https://assets.hemmings.com/uimage/60396472-770-0@2X.jpg?rev=21", "https://assets.hemmings.com/uimage/60396473-770-0@2X.jpg?rev=21", "https://assets.hemmings.com/uimage/60396474-770-0@2X.jpg?rev=21", "https://assets.hemmings.com/uimage/60396475-770-0@2X.jpg?rev=21", "https://assets.hemmings.com/uimage/60396476-770-0@2X.jpg?rev=21", "https://assets.hemmings.com/uimage/60396477-770-0@2X.jpg?rev=21", "https://assets.hemmings.com/uimage/60396478-770-0@2X.jpg?rev=21", "https://assets.hemmings.com/uimage/60396479-770-0@2X.jpg?rev=21", "https://assets.hemmings.com/uimage/60396480-770-0@2X.jpg?rev=21", "https://assets.hemmings.com/uimage/60396481-770-0@2X.jpg?rev=21", "https://assets.hemmings.com/uimage/60396482-770-0@2X.jpg?rev=21", "https://assets.hemmings.com/uimage/60396483-770-0@2X.jpg?rev=21", "https://assets.hemmings.com/uimage/60396484-770-0@2X.jpg?rev=21", "https://assets.hemmings.com/uimage/60396485-770-0@2X.jpg?rev=21", "https://assets.hemmings.com/uimage/60396486-770-0@2X.jpg?rev=21", "https://assets.hemmings.com/uimage/60396487-770-0@2X.jpg?rev=21", "https://assets.hemmings.com/uimage/60396488-770-0@2X.jpg?rev=21", "https://assets.hemmings.com/uimage/60396489-770-0@2X.jpg?rev=21", "https://assets.hemmings.com/uimage/60396490-770-0@2X.jpg?rev=21", "https://assets.hemmings.com/uimage/60396491-770-0@2X.jpg?rev=21", "https://assets.hemmings.com/uimage/60396492-770-0@2X.jpg?rev=21", "https://assets.hemmings.com/uimage/60396493-770-0@2X.jpg?rev=21"], "mileage": 704.0, "seller_name": "Fast Lane Classic Cars", "title": "1966 Ford Mustang for Sale", "total_results": " 133", "price": "24995", "page_count": 9.0, "year": "1966", "href": "https://www.hemmings.com/classifieds/dealer/ford/mustang/1999015.html", "brand": "Ford", "reference_id": "1999015", "kilometers": 1132.7359999999999, "model": "Mustang", "specs": {"Interior:": "Black", "Location:": "St Charles, Missouri,  63301", "description": ["This 1966 Ford Mustang for sale has a 302 C.I. Performance Built V8 w/ 4BBL Carb, Automatic Transmission, Ford 9'' Rear w/ 2.80:1 Ratio, Custom Charcoal Exterior w/ Black Stripes, All New Black Interior, AM/FM Custom Auto Sound Stereo, Wood Wheel, Fog Lights, Emergency Flashers, Padded Dash, Day/Night Rear View Mirror, LED Interior Lights, 17'' Chrome Wheels, Ford Racing Valve Covers & Air Cleaner, LED Halo Running Lights, Mildly Customized '66 Mustang Coupe w/ Freshly Built 302!"], "Exterior:": "Charcoal Gray", "Condition:": "Excellent", "Transmission:": "Auto", "Mileage:": "704"}},
{"src": ["https://assets.hemmings.com/uimage/59401917-770-0@2X.jpg?rev=1", "https://assets.hemmings.com/uimage/59401918-770-0@2X.jpg?rev=1", "https://assets.hemmings.com/uimage/59401919-770-0@2X.jpg?rev=1", "https://assets.hemmings.com/uimage/59401920-770-0@2X.jpg?rev=1", "https://assets.hemmings.com/uimage/59401921-770-0@2X.jpg?rev=1", "https://assets.hemmings.com/uimage/59401922-770-0@2X.jpg?rev=1", "https://assets.hemmings.com/uimage/59401923-770-0@2X.jpg?rev=1", "https://assets.hemmings.com/uimage/59401924-770-0@2X.jpg?rev=1", "https://assets.hemmings.com/uimage/59401925-770-0@2X.jpg?rev=1", "https://assets.hemmings.com/uimage/59401926-770-0@2X.jpg?rev=1", "https://assets.hemmings.com/uimage/59401927-770-0@2X.jpg?rev=1", "https://assets.hemmings.com/uimage/59401928-770-0@2X.jpg?rev=1", "https://assets.hemmings.com/uimage/59401929-770-0@2X.jpg?rev=1", "https://assets.hemmings.com/uimage/59401930-770-0@2X.jpg?rev=1", "https://assets.hemmings.com/uimage/59401931-770-0@2X.jpg?rev=1", "https://assets.hemmings.com/uimage/59401932-770-0@2X.jpg?rev=1", "https://assets.hemmings.com/uimage/59401933-770-0@2X.jpg?rev=1", "https://assets.hemmings.com/uimage/59401934-770-0@2X.jpg?rev=1", "https://assets.hemmings.com/uimage/59401935-770-0@2X.jpg?rev=1", "https://assets.hemmings.com/uimage/59401936-770-0@2X.jpg?rev=1", "https://assets.hemmings.com/uimage/59401937-770-0@2X.jpg?rev=1", "https://assets.hemmings.com/uimage/59401938-770-0@2X.jpg?rev=1", "https://assets.hemmings.com/uimage/59401939-770-0@2X.jpg?rev=1", "https://assets.hemmings.com/uimage/59401940-770-0@2X.jpg?rev=1", "https://assets.hemmings.com/uimage/59401941-770-0@2X.jpg?rev=1", "https://assets.hemmings.com/uimage/59401942-770-0@2X.jpg?rev=1", "https://assets.hemmings.com/uimage/59401943-770-0@2X.jpg?rev=1", "https://assets.hemmings.com/uimage/59401944-770-0@2X.jpg?rev=1", "https://assets.hemmings.com/uimage/59401945-770-0@2X.jpg?rev=1", "https://assets.hemmings.com/uimage/59401946-770-0@2X.jpg?rev=1", "https://assets.hemmings.com/uimage/59401947-770-0@2X.jpg?rev=1", "https://assets.hemmings.com/uimage/59401948-770-0@2X.jpg?rev=1", "https://assets.hemmings.com/uimage/59401949-770-0@2X.jpg?rev=1", "https://assets.hemmings.com/uimage/59401950-770-0@2X.jpg?rev=1", "https://assets.hemmings.com/uimage/59401951-770-0@2X.jpg?rev=1", "https://assets.hemmings.com/uimage/59401952-770-0@2X.jpg?rev=1", "https://assets.hemmings.com/uimage/59401953-770-0@2X.jpg?rev=1", "https://assets.hemmings.com/uimage/59401954-770-0@2X.jpg?rev=1", "https://assets.hemmings.com/uimage/59401955-770-0@2X.jpg?rev=1", "https://assets.hemmings.com/uimage/59401956-770-0@2X.jpg?rev=1", "https://assets.hemmings.com/uimage/59401957-770-0@2X.jpg?rev=1", "https://assets.hemmings.com/uimage/59401958-770-0@2X.jpg?rev=1", "https://assets.hemmings.com/uimage/59401959-770-0@2X.jpg?rev=1", "https://assets.hemmings.com/uimage/59401960-770-0@2X.jpg?rev=1", "https://assets.hemmings.com/uimage/59401961-770-0@2X.jpg?rev=1", "https://assets.hemmings.com/uimage/59401962-770-0@2X.jpg?rev=1", "https://assets.hemmings.com/uimage/59401963-770-0@2X.jpg?rev=1", "https://assets.hemmings.com/uimage/59401964-770-0@2X.jpg?rev=1", "https://assets.hemmings.com/uimage/59401965-770-0@2X.jpg?rev=1", "https://assets.hemmings.com/uimage/59401966-770-0@2X.jpg?rev=1"], "mileage": 9542.0, "seller_name": "Masterpiece Vintage Cars LLC", "title": "1965 Ford Mustang for Sale", "total_results": " 133", "price": "19900", "page_count": 9.0, "year": "1965", "href": "https://www.hemmings.com/classifieds/dealer/ford/mustang/1960130.html", "brand": "Ford", "reference_id": "1960130", "kilometers": 15353.078, "model": "Mustang", "specs": {"Interior:": "White Crinkle Vinyl with Black Appointments", "Location:": "Whiteland, Indiana,  46184", "description": ["Engine: 260ci 164HP 2BBL V8 F Code", "Transmission: C4 Automatic RWD", "Mileage: 9542 Miles on Rebuild", "VIN: 5F07F196241", "Exterior Color: Raven Black", "Interior Color: White Crinkle Vinyl with Black Appointments", "True 1964 1/2 Custom Chrome Wheels", "Southern Car 3.00:1 Rear"], "Exterior:": "Raven Black", "Condition:": "Excellent", "Transmission:": "Auto", "Mileage:": "9542"}},
{"src": ["https://assets.hemmings.com/uimage/60157816-770-0@2X.jpg?rev=1", "https://assets.hemmings.com/uimage/60157813-770-0@2X.jpg?rev=1", "https://assets.hemmings.com/uimage/60157814-770-0@2X.jpg?rev=1", "https://assets.hemmings.com/uimage/60157815-770-0@2X.jpg?rev=1", "https://assets.hemmings.com/uimage/60157817-770-0@2X.jpg?rev=1", "https://assets.hemmings.com/uimage/60157818-770-0@2X.jpg?rev=1", "https://assets.hemmings.com/uimage/60157819-770-0@2X.jpg?rev=1", "https://assets.hemmings.com/uimage/60157820-770-0@2X.jpg?rev=1", "https://assets.hemmings.com/uimage/60157821-770-0@2X.jpg?rev=1", "https://assets.hemmings.com/uimage/60157822-770-0@2X.jpg?rev=1"], "mileage": "", "seller_name": "Goldenrod Garage", "title": "1966 Ford Mustang for Sale", "total_results": " 133", "price": "17900", "page_count": 9.0, "year": "1966", "href": "https://www.hemmings.com/classifieds/dealer/ford/mustang/1998563.html", "brand": "Ford", "reference_id": "1998563", "kilometers": "", "model": "Mustang", "specs": {"Transmission:": "Manual", "Location:": "Freeport, Maine,  04032", "Condition:": "Excellent", "description": ["1966 Mustang convertible,refurbished to factory specs awhile ago,and still presenting well-new paint,top,and interior,with the economical six cylinder engine and three speed standard transmission.Fun ready.  $17,900."]}}
]